setup.py
Raw_distributions/Binomialdistribution.py
Raw_distributions/Gaussiandistribution.py
Raw_distributions/Generaldistribution.py
Raw_distributions/__init__.py
Raw_distributions.egg-info/PKG-INFO
Raw_distributions.egg-info/SOURCES.txt
Raw_distributions.egg-info/dependency_links.txt
Raw_distributions.egg-info/not-zip-safe
Raw_distributions.egg-info/top_level.txt