Metadata-Version: 1.0
Name: Raw-distributions
Version: 0.1
Summary: Gaussian distributions
Home-page: UNKNOWN
Author: Rawan Galal
Author-email: UNKNOWN
License: UNKNOWN
Platform: UNKNOWN
